Metadata-Version: 2.1
Name: lib-dzne-basetables
Version: 0.4.1
Summary: Libary for basetables. 
Author-email: Johannes <johannes-programming@posteo.org>
License: Copyright © 2022 Johannes Horler
Project-URL: Source, https://github.com/johannes-programming/lib_dzne_basetables
Project-URL: Download, https://pypi.org/project/lib-dzne-basetables/#files
Keywords: dzne
Classifier: License :: OSI Approved :: MIT License
Classifier: Programming Language :: Python
Classifier: Programming Language :: Python :: 3
Requires-Python: >=3.11
License-File: LICENSE.txt
Requires-Dist: pandas >=1.4.2
Requires-Dist: na-quantors >=1.0
